yamily/__init__.py
yamily/_cli.py
yamily/_graphviz.py
yamily/yaml.py
yamily-0.2.0.dist-info/COPYING
yamily-0.2.0.dist-info/METADATA
yamily-0.2.0.dist-info/WHEEL
yamily-0.2.0.dist-info/entry_points.txt
yamily-0.2.0.dist-info/top_level.txt
yamily-0.2.0.dist-info/RECORD
