Metadata-Version: 2.1
Name: yamily
Version: 0.2.0
Summary: Define family trees in YAML
Home-page: https://git.hammerle.me/fphammerle/yamily
Author: Fabian Peter Hammerle
Author-email: fabian@hammerle.me
License: GPLv3+
Keywords: ancestors,family-tree,genealogy,plot,visualize
Platform: UNKNOWN
Classifier: Development Status :: 2 - Pre-Alpha
Classifier: Intended Audience :: End Users/Desktop
Classifier: License :: OSI Approved :: GNU General Public License v3 or later (GPLv3+)
Classifier: Operating System :: OS Independent
Classifier: Programming Language :: Python :: 3
Classifier: Topic :: Database
Classifier: Topic :: Sociology :: Genealogy
Classifier: Topic :: Utilities
Provides-Extra: graphviz
Requires-Dist: graphviz (>=0.7) ; extra == 'graphviz'
Provides-Extra: yaml
Requires-Dist: PyYAML ; extra == 'yaml'
